mergetool/__init__.py
mergetool/imgdiff.py
qgitc/__init__.py
qgitc/aboutdialog.py
qgitc/actionrunner.py
qgitc/aichatbot.py
qgitc/aichathistory.py
qgitc/aichathistorypanel.py
qgitc/aichattitlegenerator.py
qgitc/aichatwindow.py
qgitc/aicommitmessage.py
qgitc/application.py
qgitc/applicationbase.py
qgitc/blamefetcher.py
qgitc/blameline.py
qgitc/blamesourceviewer.py
qgitc/blameview.py
qgitc/blamewindow.py
qgitc/branchcomparewindow.py
qgitc/cancelevent.py
qgitc/changeauthordialog.py
qgitc/colorediconbutton.py
qgitc/colorediconlabel.py
qgitc/coloredicontoolbutton.py
qgitc/coloredlabel.py
qgitc/colorschema.py
qgitc/colorwidget.py
qgitc/comboboxitemdelegate.py
qgitc/commitactioneditdialog.py
qgitc/commitactiontablemodel.py
qgitc/commitactionwidget.py
qgitc/commitdetailpanel.py
qgitc/commitmessageedit.py
qgitc/commitpanel.py
qgitc/commitsource.py
qgitc/commitwindow.py
qgitc/common.py
qgitc/conflictlog.py
qgitc/datafetcher.py
qgitc/difffetcher.py
qgitc/difffinder.py
qgitc/diffutils.py
qgitc/diffview.py
qgitc/emptystatelistview.py
qgitc/events.py
qgitc/excepthandler.py
qgitc/filestatus.py
qgitc/findconstants.py
qgitc/findsubmodules.py
qgitc/findwidget.py
qgitc/fontchooserwidget.py
qgitc/githubcopilotlogindialog.py
qgitc/gitprogressdialog.py
qgitc/gitutils.py
qgitc/gitview.py
qgitc/gotodialog.py
qgitc/languagedata.py
qgitc/linkeditdialog.py
qgitc/linkeditwidget.py
qgitc/llm.py
qgitc/llmprovider.py
qgitc/logsfetcher.py
qgitc/logsfetchergitworker.py
qgitc/logsfetcherimpl.py
qgitc/logsfetcherqprocessworker.py
qgitc/logsfetcherworkerbase.py
qgitc/logview.py
qgitc/main.py
qgitc/mainwindow.py
qgitc/markdownhighlighter.py
qgitc/menubutton.py
qgitc/mergetool.py
qgitc/mergewidget.py
qgitc/namefetcher.py
qgitc/newversiondialog.py
qgitc/ntpdatetime.py
qgitc/otelenv.py
qgitc/otelimpl.py
qgitc/patchviewer.py
qgitc/pickbranchwindow.py
qgitc/preferences.py
qgitc/repopathinput.py
qgitc/revisionpanel.py
qgitc/searchlineedit.py
qgitc/settings.py
qgitc/shell.py
qgitc/sourceviewer.py
qgitc-6.3.8.dist-info/licenses/LICENSE
qgitc-6.3.8.dist-info/METADATA
qgitc-6.3.8.dist-info/WHEEL
qgitc-6.3.8.dist-info/entry_points.txt
qgitc-6.3.8.dist-info/top_level.txt
qgitc-6.3.8.dist-info/RECORD
