Metadata-Version: 2.4
Name: qgitc
Version: 6.3.8
Summary: A cross-platform Git GUI tool
Author-email: Weitian Leung <weitianleung@gmail.com>
License-Expression: Apache-2.0
Project-URL: Homepage, https://github.com/timxx/qgitc
Project-URL: Repository, https://github.com/timxx/qgitc.git
Project-URL: Issues, https://github.com/timxx/qgitc/issues
Keywords: git,conflict,viewer,blame,ai,llm,log,commit,code review
Classifier: Operating System :: POSIX
Classifier: Operating System :: POSIX :: BSD
Classifier: Operating System :: POSIX :: Linux
Classifier: Operating System :: Microsoft :: Windows
Classifier: Programming Language :: Python :: 3
Requires-Python: >=3.6
License-File: LICENSE
Requires-Dist: PySide6-Essentials>=6.3.0; sys_platform != "linux"
Requires-Dist: PySide6>=6.2.0; sys_platform == "linux"
Requires-Dist: chardet
Requires-Dist: psutil; sys_platform == "win32"
Requires-Dist: packaging
Requires-Dist: opentelemetry-api
Requires-Dist: opentelemetry-sdk
Requires-Dist: opentelemetry-exporter-otlp-proto-http
Requires-Dist: pygit2; sys_platform == "win32"
Dynamic: description
Dynamic: description-content-type
Dynamic: license-file
